README.txt
setup.cfg
setup.py
docs/HISTORY.txt
docs/INSTALL.txt
docs/LICENSE.GPL
docs/LICENSE.txt
iccommunity/__init__.py
iccommunity.mediawiki.egg-info/PKG-INFO
iccommunity.mediawiki.egg-info/SOURCES.txt
iccommunity.mediawiki.egg-info/dependency_links.txt
iccommunity.mediawiki.egg-info/entry_points.txt
iccommunity.mediawiki.egg-info/namespace_packages.txt
iccommunity.mediawiki.egg-info/not-zip-safe
iccommunity.mediawiki.egg-info/requires.txt
iccommunity.mediawiki.egg-info/top_level.txt
iccommunity/mediawiki/README.txt
iccommunity/mediawiki/TODO.txt
iccommunity/mediawiki/__init__.py
iccommunity/mediawiki/browser.txt
iccommunity/mediawiki/config.py
iccommunity/mediawiki/configure.zcml
iccommunity/mediawiki/interfaces.py
iccommunity/mediawiki/preferences.py
iccommunity/mediawiki/revision.txt
iccommunity/mediawiki/setuphandlers.py
iccommunity/mediawiki/version.txt
iccommunity/mediawiki/Extensions/__init__.py
iccommunity/mediawiki/Extensions/install.py
iccommunity/mediawiki/browser/__init__.py
iccommunity/mediawiki/browser/admin.py
iccommunity/mediawiki/browser/admin.zcml
iccommunity/mediawiki/browser/configure.zcml
iccommunity/mediawiki/profiles/default/import_steps.xml
iccommunity/mediawiki/tests/__init__.py
iccommunity/mediawiki/tests/base.py
iccommunity/mediawiki/tests/roles_mapper_configlet.txt
iccommunity/mediawiki/tests/sql_server_configlet.txt
iccommunity/mediawiki/tests/test_functional.py
iccommunity/mediawiki/tests/test_utilities.py