Metadata-Version: 1.0
Name: iccommunity.mediawiki
Version: 1.0-dev-r371
Summary: icCommunity.Mediawiki
Home-page: http://www.platecom.com/productos/iccommunity.mediawiki/
Author: Inter-Cultura Consultora SRL - Ibai Sistemas SA - Eusko Ikaskuntza-Sociedad de Estudios Vascos
Author-email: dev@inter-cultura.com
License: GPL
Keywords: iccommunity,platecom,icsemantic,mediawiki,integration
Platform: UNKNOWN
Classifier: Topic :: Documentation
Classifier: Environment :: Web Environment
Classifier: Framework :: Plone
Classifier: Development Status :: 4 - Beta
Classifier: Intended Audience :: Information Technology
Classifier: License :: OSI Approved :: GNU General Public License (GPL)
Classifier: Operating System :: OS Independent
Classifier: Programming Language :: Python
